Metadata-Version: 2.1
Name: signalr-async
Version: 2.3.1
Summary: Python SignalR async client
Home-page: https://github.com/sam-mosleh/signalr-async
License: MIT
Keywords: SignalR,SignalR client,Real-time messaging
Author: Sam Mosleh
Author-email: sam.mosleh@ut.ac.ir
Requires-Python: >=3.8,<4.0
Classifier: License :: OSI Approved :: MIT License
Classifier: Programming Language :: Python :: 3
Classifier: Programming Language :: Python :: 3.8
Classifier: Programming Language :: Python :: 3.9
Requires-Dist: aiohttp (>=3.6.0,<4.0.0)
Requires-Dist: msgpack (>=1.0.2,<2.0.0)
